src/__init__.py
src/module.py
kriptan-0.1.dist-info/METADATA
kriptan-0.1.dist-info/WHEEL
kriptan-0.1.dist-info/top_level.txt
kriptan-0.1.dist-info/RECORD
